myvariant/__init__.py
myvariant-1.0.0.dist-info/METADATA
myvariant-1.0.0.dist-info/RECORD
myvariant-1.0.0.dist-info/WHEEL
myvariant-1.0.0.dist-info/top_level.txt
