Metadata-Version: 2.1
Name: myvariant
Version: 1.0.0
Summary: Python Client for MyVariant.Info services.
Home-page: https://github.com/biothings/myvariant.py
Author: Chunlei Wu, Cyrus Afrasiabi, Sebastien Lelong
Author-email: cwu@scripps.edu
License: BSD
Keywords: biology variant annotation web service client api myvariant
Platform: UNKNOWN
Classifier: Programming Language :: Python
Classifier: Programming Language :: Python :: 2
Classifier: Programming Language :: Python :: 2.7
Classifier: Programming Language :: Python :: 3
Classifier: Programming Language :: Python :: 3.4
Classifier: Programming Language :: Python :: 3.5
Classifier: Programming Language :: Python :: 3.6
Classifier: Programming Language :: Python :: 3.7
Classifier: Development Status :: 5 - Production/Stable
Classifier: License :: OSI Approved :: BSD License
Classifier: Operating System :: POSIX
Classifier: Operating System :: MacOS :: MacOS X
Classifier: Operating System :: Microsoft :: Windows
Classifier: Operating System :: OS Independent
Classifier: Intended Audience :: Science/Research
Classifier: Intended Audience :: Developers
Classifier: Topic :: Utilities
Classifier: Topic :: Scientific/Engineering :: Bio-Informatics
Requires-Dist: biothings-client (>=0.2.0)
